examples/__init__.py
examples/hello_world/__init__.py
examples/hello_world/external_dataset/__init__.py
examples/hello_world/external_dataset/generate_external_dataset.py
examples/hello_world/external_dataset/python_hello_world.py
examples/hello_world/external_dataset/pytorch_hello_world.py
examples/hello_world/external_dataset/tensorflow_hello_world.py
examples/hello_world/petastorm_dataset/__init__.py
examples/hello_world/petastorm_dataset/generate_petastorm_dataset.py
examples/hello_world/petastorm_dataset/pyspark_hello_world.py
examples/hello_world/petastorm_dataset/python_hello_world.py
examples/hello_world/petastorm_dataset/pytorch_hello_world.py
examples/hello_world/petastorm_dataset/tensorflow_hello_world.py
examples/imagenet/__init__.py
examples/imagenet/generate_petastorm_imagenet.py
examples/imagenet/schema.py
examples/mnist/__init__.py
examples/mnist/generate_petastorm_mnist.py
examples/mnist/pytorch_example.py
examples/mnist/schema.py
examples/mnist/tf_example.py
examples/mnist/tests/__init__.py
examples/mnist/tests/conftest.py
examples/mnist/tests/test_pytorch_mnist.py
examples/mnist/tests/test_tf_mnist.py
examples/spark_dataset_converter/__init__.py
examples/spark_dataset_converter/pytorch_converter_example.py
examples/spark_dataset_converter/tensorflow_converter_example.py
examples/spark_dataset_converter/utils.py
petastorm/__init__.py
petastorm/arrow_reader_worker.py
petastorm/cache.py
petastorm/codecs.py
petastorm/errors.py
petastorm/fs_utils.py
petastorm/generator.py
petastorm/local_disk_cache.py
petastorm/namedtuple_gt_255_fields.py
petastorm/ngram.py
petastorm/predicates.py
petastorm/py_dict_reader_worker.py
petastorm/pytorch.py
petastorm/reader.py
petastorm/selectors.py
petastorm/spark_utils.py
petastorm/tf_utils.py
petastorm/transform.py
petastorm/unischema.py
petastorm/utils.py
petastorm/weighted_sampling_reader.py
petastorm/benchmark/__init__.py
petastorm/benchmark/cli.py
petastorm/benchmark/dummy_reader.py
petastorm/benchmark/throughput.py
petastorm-0.12.1.dist-info/LICENSE
petastorm-0.12.1.dist-info/METADATA
petastorm-0.12.1.dist-info/NOTICE
petastorm-0.12.1.dist-info/WHEEL
petastorm-0.12.1.dist-info/entry_points.txt
petastorm-0.12.1.dist-info/top_level.txt
petastorm-0.12.1.dist-info/RECORD
