Metadata-Version: 2.1
Name: petastorm
Version: 0.12.1
Summary: Petastorm is a library enabling the use of Parquet storage from Tensorflow, Pytorch, and other Python-based ML training frameworks.
Home-page: https://github.com/uber/petastorm
Author: Uber Technologies, Inc.
License: Apache License, Version 2.0
Platform: UNKNOWN
Classifier: Environment :: Console
Classifier: Environment :: Web Environment
Classifier: Intended Audience :: Developers
Classifier: Intended Audience :: Science/Research
Classifier: License :: OSI Approved :: Apache Software License
Classifier: Programming Language :: Python :: 3.4
Classifier: Programming Language :: Python :: 3.5
Classifier: Programming Language :: Python :: 3.6
Classifier: Programming Language :: Python :: 3.7
Classifier: Programming Language :: Python :: 3.8
Requires-Python: >=3
Requires-Dist: dill (>=0.2.1)
Requires-Dist: diskcache (>=3.0.0)
Requires-Dist: future (>=0.10.2)
Requires-Dist: numpy (>=1.13.3)
Requires-Dist: packaging (>=15.0)
Requires-Dist: pandas (>=0.19.0)
Requires-Dist: psutil (>=4.0.0)
Requires-Dist: pyspark (>=2.1.0)
Requires-Dist: pyzmq (>=14.0.0)
Requires-Dist: pyarrow (>=0.17.1)
Requires-Dist: six (>=1.5.0)
Requires-Dist: fsspec
Provides-Extra: docs
Requires-Dist: sphinx (>=1.2.2) ; extra == 'docs'
Requires-Dist: alabaster (>=0.7.11) ; extra == 'docs'
Provides-Extra: opencv
Requires-Dist: opencv-python (>=3.2.0.6) ; extra == 'opencv'
Provides-Extra: s3fs
Requires-Dist: s3fs (>=0.5.0) ; extra == 's3fs'
Provides-Extra: test
Requires-Dist: Pillow (>=6.2.1) ; extra == 'test'
Requires-Dist: codecov (>=2.0.15) ; extra == 'test'
Requires-Dist: flake8 ; extra == 'test'
Requires-Dist: gcsfs (>=0.2.0) ; extra == 'test'
Requires-Dist: mock (>=2.0.0) ; extra == 'test'
Requires-Dist: mypy ; extra == 'test'
Requires-Dist: opencv-python (>=3.2.0.6) ; extra == 'test'
Requires-Dist: pylint (>=1.9) ; extra == 'test'
Requires-Dist: pytest (>=3.0.0) ; extra == 'test'
Requires-Dist: pytest-cov (>=2.5.1) ; extra == 'test'
Requires-Dist: pytest-forked (>=0.2) ; extra == 'test'
Requires-Dist: pytest-logger (>=0.4.0) ; extra == 'test'
Requires-Dist: pytest-timeout (>=1.3.3) ; extra == 'test'
Requires-Dist: requests (>=2.22.0) ; extra == 'test'
Requires-Dist: s3fs (>=0.0.1) ; extra == 'test'
Requires-Dist: gcsfs ; extra == 'test'
Requires-Dist: types-pytz (==2021.1.0) ; extra == 'test'
Requires-Dist: types-six (==0.1.7) ; extra == 'test'
Provides-Extra: tf
Requires-Dist: tensorflow (>=1.14.0) ; extra == 'tf'
Provides-Extra: tf_gpu
Requires-Dist: tensorflow-gpu (>=1.14.0) ; extra == 'tf_gpu'
Provides-Extra: torch
Requires-Dist: torchvision (>=0.2.1) ; extra == 'torch'
Requires-Dist: torch (>=1.5.0) ; extra == 'torch'
